RAKE/RAKE.py
RAKE/__init__.py
RAKE/stoplists/FoxStopList.py
RAKE/stoplists/GoogleSearchStopList.py
RAKE/stoplists/MySQLStopList.py
RAKE/stoplists/NLTKStopList.py
RAKE/stoplists/RanksNLLongStopList.py
RAKE/stoplists/RanksNLStoplist.py
RAKE/stoplists/SmartStopList.py
RAKE/stoplists/__init__.py
python_rake-1.5.0.dist-info/LICENSE
python_rake-1.5.0.dist-info/METADATA
python_rake-1.5.0.dist-info/WHEEL
python_rake-1.5.0.dist-info/top_level.txt
python_rake-1.5.0.dist-info/RECORD
