Metadata-Version: 1.2
Name: python-rake
Version: 1.5.0
Summary: A python module implementing the Rapid Automatic Keyword Extraction algorithm.
Home-page: https://github.com/fabianvf/python-rake
Author: Tomás Pinho <me@tomaspinho.com>, Fabian von Feilitzsch <fabian@fabianism.us>
Author-email: fabian@fabianism.us
License: MIT
Keywords: text mining data mining natural language processing
Platform: UNKNOWN
Classifier: Development Status :: 5 - Production/Stable
Classifier: Intended Audience :: Developers
Classifier: Topic :: Scientific/Engineering :: Artificial Intelligence
Classifier: Topic :: Scientific/Engineering :: Information Analysis
Classifier: Topic :: Software Development :: Libraries :: Python Modules
Classifier: Topic :: Text Processing :: Indexing
Classifier: License :: OSI Approved :: MIT License
Classifier: Programming Language :: Python :: 3
Classifier: Programming Language :: Python :: 3.6
Classifier: Programming Language :: Python :: 3.7
Classifier: Programming Language :: Python :: 3.8
Classifier: Programming Language :: Python :: 3.9
Requires-Python: >=3.6
